README.md
setup.py
src/ko_sentence_transformers/__init__.py
src/ko_sentence_transformers.egg-info/PKG-INFO
src/ko_sentence_transformers.egg-info/SOURCES.txt
src/ko_sentence_transformers.egg-info/dependency_links.txt
src/ko_sentence_transformers.egg-info/requires.txt
src/ko_sentence_transformers.egg-info/top_level.txt
src/ko_sentence_transformers/models/KoBertTransformer.py
src/ko_sentence_transformers/models/__init__.py
src/ko_sentence_transformers/models/tokenizer/KoBertTokenizer.py
src/ko_sentence_transformers/models/tokenizer/__init__.py