Metadata-Version: 2.1
Name: ko-sentence-transformers
Version: 0.3
Summary: UNKNOWN
Home-page: UNKNOWN
Author: Junghyun Gan
Author-email: jhgan00@yonsei.ac.kr
License: Apache2
Platform: UNKNOWN
Requires-Python: >=3
